rtl/qp/rdma_rc_qp.v
// RDMA RC QP状态机RTL设计（修复qp_ready置位时序）
// 路径：rtl/qp/rdma_rc_qp.v
module rdma_rc_qp #(
    parameter QPN_WIDTH = 16  // QPN（Queue Pair Number）位宽
)(
    input  wire                 clk,        // 系统时钟（100MHz）
    input  wire                 rst_n,      // 异步低电平复位
    input  wire [QPN_WIDTH-1:0] local_qpn,  // 本地QP编号
    input  wire [QPN_WIDTH-1:0] remote_qpn, // 远程QP编号
    input  wire                 cfg_valid,  // QP配置有效信号
    input  wire                 cmd_connect,// 连接命令（触发RTR/RTS）
    input  wire                 cmd_disconnect, // 断开命令（回到Reset）
    output reg  [2:0]           qp_state,   // QP当前状态（3位编码）
    output reg                  qp_ready    // QP就绪信号（状态稳定后置位）
);

// ========== RDMA RC QP标准状态定义 ==========
localparam RESET  = 3'b000; // 复位状态（初始）
localparam INIT   = 3'b001; // 初始化状态（配置完成）
localparam RTR    = 3'b010; // 接收就绪（收到远程QP连接请求）
localparam RTS    = 3'b011; // 发送就绪（双向连接建立，可传输数据）
localparam ERROR  = 3'b111; // 错误状态（配置/命令异常）

// ========== 内部寄存器 ==========
reg [QPN_WIDTH-1:0] local_qpn_reg;  // 本地QPN配置寄存器
reg [QPN_WIDTH-1:0] remote_qpn_reg; // 远程QPN配置寄存器
reg                 cfg_done;       // 配置完成标志

// ========== 配置寄存器逻辑 ==========
always @(posedge clk or negedge rst_n) begin
    if (!rst_n) begin
        local_qpn_reg  <= {QPN_WIDTH{1'b0}};
        remote_qpn_reg <= {QPN_WIDTH{1'b0}};
        cfg_done       <= 1'b0;
    end else if (cfg_valid && !cfg_done) begin
        // 锁存本地QPN，远程QPN需在连接阶段配置
        local_qpn_reg  <= local_qpn;
        cfg_done       <= 1'b1; // 配置完成标志置位
    end else if (cmd_connect && cfg_done && (qp_state == INIT)) begin
        // 连接阶段锁存远程QPN
        remote_qpn_reg <= remote_qpn;
    end else if (cmd_disconnect) begin
        // 断开连接，清空配置
        local_qpn_reg  <= {QPN_WIDTH{1'b0}};
        remote_qpn_reg <= {QPN_WIDTH{1'b0}};
        cfg_done       <= 1'b0;
    end
end

// ========== QP核心状态机（修复qp_ready置位时序） ==========
always @(posedge clk or negedge rst_n) begin
    if (!rst_n) begin
        qp_state <= RESET;
        qp_ready <= 1'b0;
    end else begin
        case (qp_state)
            RESET: begin
                // 复位状态：配置有效则进入Init，同时置位ready
                if (cfg_valid) begin
                    qp_state <= INIT;
                    qp_ready <= 1'b1; // 状态切换时直接置位ready
                end else begin
                    qp_state <= RESET;
                    qp_ready <= 1'b0;
                end
            end
            INIT: begin
                // 初始化状态：配置完成+连接命令+远程QPN非0 → 进入RTR
                if (cfg_done && cmd_connect && (remote_qpn != {QPN_WIDTH{1'b0}})) begin
                    qp_state <= RTR;
                    qp_ready <= 1'b1; // 状态切换时直接置位ready
                end else if (cmd_disconnect) begin
                    qp_state <= RESET;
                    qp_ready <= 1'b0;
                end else begin
                    qp_state <= INIT;
                    qp_ready <= 1'b1; // 保持INIT状态，ready始终置位
                end
            end
            RTR: begin
                // 接收就绪：再次收到连接命令（远程QP确认）→ 进入RTS
                if (cmd_connect && (remote_qpn_reg == remote_qpn)) begin
                    qp_state <= RTS;
                    qp_ready <= 1'b1; // 状态切换时直接置位ready
                end else if (cmd_disconnect) begin
                    qp_state <= RESET;
                    qp_ready <= 1'b0;
                end else begin
                    qp_state <= RTR;
                    qp_ready <= 1'b1; // 保持RTR状态，ready始终置位
                end
            end
            RTS: begin
                // 发送就绪：核心工作状态，断开命令则回到Reset
                if (cmd_disconnect) begin
                    qp_state <= RESET;
                    qp_ready <= 1'b0;
                end else begin
                    qp_state <= RTS;
                    qp_ready <= 1'b1; // 保持RTS状态，ready始终置位
                end
            end
            default: begin
                // 异常状态：回到Reset
                qp_state <= ERROR;
                qp_ready <= 1'b0;
            end
        endcase
    end
end

endmodule

verification/tb_rdma_rc_qp.sv
// RDMA RC QP状态机验证测试台（SystemVerilog）
// 路径：verification/tb_rdma_rc_qp.sv
module tb_rdma_rc_qp;

// ========== 参数定义 ==========
parameter QPN_WIDTH = 16;
parameter CLK_PERIOD = 10; // 时钟周期10ns（100MHz）

// ========== 信号声明 ==========
logic                 clk;
logic                 rst_n;
logic [QPN_WIDTH-1:0] local_qpn;
logic [QPN_WIDTH-1:0] remote_qpn;
logic                 cfg_valid;
logic                 cmd_connect;
logic                 cmd_disconnect;
logic [2:0]           qp_state;
logic                 qp_ready;

// ========== RDMA RC QP状态宏定义（与DUT对齐） ==========
localparam RESET  = 3'b000;
localparam INIT   = 3'b001;
localparam RTR    = 3'b010;
localparam RTS    = 3'b011;
localparam ERROR  = 3'b111;

// ========== 实例化DUT（RTL模块） ==========
rdma_rc_qp #(
    .QPN_WIDTH(QPN_WIDTH)
) u_rdma_rc_qp (
    .clk            (clk),
    .rst_n          (rst_n),
    .local_qpn      (local_qpn),
    .remote_qpn     (remote_qpn),
    .cfg_valid      (cfg_valid),
    .cmd_connect    (cmd_connect),
    .cmd_disconnect (cmd_disconnect),
    .qp_state       (qp_state),
    .qp_ready       (qp_ready)
);
// ========== 时钟生成 ==========
initial begin
    clk = 1'b0;
    forever #(CLK_PERIOD/2) clk = ~clk;
end

// ========== 核心测试激励序列 ==========
initial begin
    // 1. 初始化信号
    rst_n          = 1'b0;
    local_qpn      = 16'h1234; // 本地QPN配置
    remote_qpn     = 16'h0000; // 远程QPN初始为0
    cfg_valid      = 1'b0;
    cmd_connect    = 1'b0;
    cmd_disconnect = 1'b0;

    // 2. 释放复位
    #20 rst_n = 1'b1;
    $display("[%0t ns] 复位释放，进入RESET状态", $time);

    // 3. 配置QP，进入INIT状态
    #10 cfg_valid = 1'b1;
    #10 cfg_valid = 1'b0;
    $display("[%0t ns] QP配置有效，触发进入INIT状态", $time);

    // 4. 配置远程QPN，发送连接命令，进入RTR状态
    #30 remote_qpn = 16'h5678; // 远程QPN配置为5678
    #10 cmd_connect = 1'b1;
    #10 cmd_connect = 1'b0;
    $display("[%0t ns] 发送连接命令，触发进入RTR状态", $time);

    // 5. 远程QP确认，再次发送连接命令，进入RTS状态（核心工作状态）
    #30 cmd_connect = 1'b1;
    #10 cmd_connect = 1'b0;
    $display("[%0t ns] 远程QP确认，触发进入RTS状态（数据传输就绪）", $time);

    // 6. 运行一段时间后，发送断开命令，回到RESET状态
    #100 cmd_disconnect = 1'b1;
    #10 cmd_disconnect = 1'b0;
    $display("[%0t ns] 发送断开命令，触发回到RESET状态", $time);

    // 7. 仿真结束
    #50 $display("[%0t ns] 仿真结束", $time);
    $finish;
end

// ========== 状态断言验证（SV特性，确保状态转移正确） ==========
// 断言1：复位时必须处于RESET状态
assert property (@(posedge clk) !rst_n |-> qp_state == RESET) else
    $error("[ASSERT ERROR] 复位时QP状态非RESET！");

// 断言2：配置有效后，INIT状态必须就绪
assert property (@(posedge clk) (qp_state == INIT) |-> qp_ready) else
    $error("[ASSERT ERROR] INIT状态未就绪！");

// 断言3：RTS状态必须就绪（核心工作状态）
assert property (@(posedge clk) (qp_state == RTS) |-> qp_ready) else
    $error("[ASSERT ERROR] RTS状态未就绪（无法传输数据）！");

// ========== 波形Dump（适配sim/wave目录） ==========
initial begin
    $dumpfile("../sim/wave/tb_qp.vcd"); // 波形文件输出到sim/wave
    $dumpvars(0, tb_rdma_rc_qp);       // Dump所有层级信号
    $dumpflush; // 强制刷新波形缓存

    // 新增FSDB Dump核心代码（关键）
    $fsdbDumpfile("../sim/wave/tb_qp.fsdb");  // 指定FSDB输出路径（与VCD同目录）
    $fsdbDumpvars(0, tb_rdma_rc_qp);          // Dump所有层级的信号（0表示全层级）
    $fsdbDumpMDA();                            // 可选：支持多维数组信号Dump（RDMA可能用到）
    $fsdbAutoSwitchDumpfile(1024, "../sim/wave/tb_qp.fsdb", 2); // 可选：大仿真时自动切分FSDB（按1GB切分）
end

endmodule

sim/wave/tb_qp.vcd
$date
	Tue Nov 25 03:38:00 2025
$end

$version
	Synopsys VCS version O-2018.09-SP2_Full64
$end

$timescale
	1ps
$end

$comment Csum: 1 6ed7f82f4fb090ee $end


$scope module tb_rdma_rc_qp $end
$var reg 1 ! rst_n $end
$var reg 3 " qp_state [2:0] $end
$var reg 1 # qp_ready $end
$var reg 1 $ clk $end
$var reg 16 % local_qpn [15:0] $end
$var reg 16 & remote_qpn [15:0] $end
$var reg 1 ' cfg_valid $end
$var reg 1 ( cmd_connect $end
$var reg 1 ) cmd_disconnect $end

$scope task _$$txp______assert_unnamed$$_2 $end
$upscope $end


$scope task _$$txp______assert_unnamed$$_3 $end
$upscope $end


$scope task _$$txp______assert_unnamed$$_4 $end
$upscope $end


$scope task _$$txp_fail_action_unnamed$$_2 $end
$upscope $end


$scope task _$$txp_fail_action_unnamed$$_3 $end
$upscope $end


$scope task _$$txp_fail_action_unnamed$$_4 $end
$upscope $end


$scope module u_rdma_rc_qp $end
$var wire 1 * clk $end
$var wire 1 + rst_n $end
$var wire 16 , local_qpn [15:0] $end
$var wire 16 - remote_qpn [15:0] $end
$var wire 1 . cfg_valid $end
$var wire 1 / cmd_connect $end
$var wire 1 0 cmd_disconnect $end
$var reg 3 1 qp_state [2:0] $end
$var reg 1 2 qp_ready $end
$var reg 16 3 local_qpn_reg [15:0] $end
$var reg 16 4 remote_qpn_reg [15:0] $end
$var reg 1 5 cfg_done $end
$upscope $end

$upscope $end

$enddefinitions $end

#0
$dumpvars
05
0'
0$
0(
0)
0#
0!
0.
0/
00
02
0+
b0001001000110100 %
b0000000000000000 3
b000 "
b0000000000000000 &
b0000000000000000 4
b0001001000110100 ,
b000 1
b0000000000000000 -
0*
$end
#5000
1$
1*
#10000
0$
0*
#15000
1$
1*
#20000
1!
1+
0$
0*
#25000
1$
1*
#30000
1'
1.
0$
0*
#35000
1$
1*
b0001001000110100 3
15
b001 1
b001 "
12
1#
#40000
0'
0.
0$
0*
#45000
1$
1*
#50000
0$
0*
#55000
1$
1*
#60000
0$
0*
#65000
1$
1*
#70000
b0101011001111000 &
b0101011001111000 -
0$
0*
#75000
1$
1*
#80000
1(
1/
0$
0*
#85000
1$
1*
b0101011001111000 4
b010 1
b010 "
#90000
0(
0/
0$
0*
#95000
1$
1*
#100000
0$
0*
#105000
1$
1*
#110000
0$
0*
#115000
1$
1*
#120000
1(
1/
0$
0*
#125000
1$
1*
b011 1
b011 "
#130000
0(
0/
0$
0*
#135000
1$
1*
#140000
0$
0*
#145000
1$
1*
#150000
0$
0*
#155000
1$
1*
#160000
0$
0*
#165000
1$
1*
#170000
0$
0*
#175000
1$
1*
#180000
0$
0*
#185000
1$
1*
#190000
0$
0*
#195000
1$
1*
#200000
0$
0*
#205000
1$
1*
#210000
0$
0*
#215000
1$
1*
#220000
0$
0*
#225000
1$
1*
#230000
1)
10
0$
0*
#235000
1$
1*
b0000000000000000 3
b0000000000000000 4
05
b000 1
b000 "
02
0#
#240000
0)
00
0$
0*
