rtl/pdu/rdma_rc_pdu_parser.v
// RDMA RC PDU解析模块
// 功能：解析PDU头部的Opcode/QPN/PSN字段，区分数据帧/控制帧，
//       检测Opcode错误（状态不匹配/无效Opcode）和QPN不匹配错误
// 参数化设计：兼容QP状态机位宽，支持总线位宽扩展
module rdma_rc_pdu_parser #(
    parameter QPN_WIDTH     = 16,    // 队列对号位宽（与QP状态机一致）
    parameter PSN_WIDTH     = 24,    // 包序列号位宽（RDMA标准）
    parameter OPCODE_WIDTH  = 8,     // 操作码位宽（RDMA标准8位）
    parameter DATA_WIDTH    = 64,    // PDU数据总线位宽（可扩展至128/256）
    // PDU头部字段偏移定义（64位总线大端序）
    parameter OPCODE_OFFSET = 56,    // Opcode偏移：bit56~bit63
    parameter QPN_OFFSET    = 32,    // QPN偏移：bit32~bit47
    parameter PSN_OFFSET    = 8      // PSN偏移：bit8~bit31
)(
    input  wire                                     clk,                // 系统时钟（100MHz）
    input  wire                                     rst_n,              // 异步低电平复位
    input  wire [DATA_WIDTH-1:0]                    pdu_data,           // 物理层输入的PDU数据
    input  wire                                     pdu_valid,          // PDU数据有效信号
    input  wire [2:0]                               qp_state,           // QP当前状态（来自QP状态机）
    input  wire [QPN_WIDTH-1:0]                     local_qpn,          // 本地QPN（来自QP配置）
    input  wire [QPN_WIDTH-1:0]                     remote_qpn,         // 远程QPN（来自QP配置）
    // PDU解析结果输出
    output reg  [OPCODE_WIDTH-1:0]                  pdu_opcode,         // 解析出的Opcode字段
    output reg  [QPN_WIDTH-1:0]                     pdu_qpn,            // 解析出的QPN字段
    output reg  [PSN_WIDTH-1:0]                     pdu_psn,            // 解析出的PSN字段
    output reg                                      is_data_frame,      // 数据帧标志：1=数据帧，0=非数据帧
    output reg                                      is_control_frame,   // 控制帧标志：1=控制帧，0=非控制帧
    // 错误检测输出
    output reg                                      opcode_err,         // Opcode错误：无效Opcode/状态不匹配
    output reg                                      qpn_mismatch_err,   // QPN错误：解析值与本地/远程QPN不匹配
    output reg                                      pdu_parse_done      // PDU解析完成标志
);

// QP状态定义（与QP状态机对齐）
localparam RESET  = 3'b000;    // 复位状态
localparam INIT   = 3'b001;    // 初始化状态
localparam RTR    = 3'b010;    // 接收就绪状态
localparam RTS    = 3'b011;    // 发送就绪状态（数据传输）
localparam ERROR  = 3'b111;    // 错误状态

// RDMA RC Opcode范围定义（协议标准分类）
localparam DATA_OPCODE_MIN  = {OPCODE_WIDTH{1'b0}};  // 数据帧Opcode：0x00~0x1F
localparam DATA_OPCODE_MAX  = 8'h1F;
localparam CTRL_OPCODE_MIN  = 8'h20;                 // 控制帧Opcode：0x20~0x7F
localparam CTRL_OPCODE_MAX  = 8'h7F;
localparam RESERVED_OPCODE_MIN = 8'h80;              // 保留无效Opcode：0x80~0xFF

// 内部寄存器：锁存字段值和帧类型判断结果
reg [OPCODE_WIDTH-1:0]  opcode_r;   // 锁存的Opcode字段
reg [QPN_WIDTH-1:0]     qpn_r;      // 锁存的QPN字段
reg [PSN_WIDTH-1:0]     psn_r;      // 锁存的PSN字段
reg                     data_frame_r; // 锁存的数据帧标志
reg                     ctrl_frame_r; // 锁存的控制帧标志

// 步骤1：提取PDU头部字段（组合逻辑）
// 根据偏移参数从PDU数据总线中提取Opcode/QPN/PSN
always @(*) begin
    if (pdu_valid) begin
        opcode_r = pdu_data[OPCODE_OFFSET + OPCODE_WIDTH - 1 : OPCODE_OFFSET];
        qpn_r    = pdu_data[QPN_OFFSET + QPN_WIDTH - 1 : QPN_OFFSET];
        psn_r    = pdu_data[PSN_OFFSET + PSN_WIDTH - 1 : PSN_OFFSET];
    end else begin
        opcode_r = {OPCODE_WIDTH{1'b0}};
        qpn_r    = {QPN_WIDTH{1'b0}};
        psn_r    = {PSN_WIDTH{1'b0}};
    end
end

// 步骤2：区分数据帧/控制帧（组合逻辑）
// 根据Opcode范围按RDMA协议标准分类帧类型
always @(*) begin
    if (pdu_valid) begin
        if ((opcode_r >= DATA_OPCODE_MIN) && (opcode_r <= DATA_OPCODE_MAX)) begin
            data_frame_r = 1'b1;
            ctrl_frame_r = 1'b0;
        end else if ((opcode_r >= CTRL_OPCODE_MIN) && (opcode_r <= CTRL_OPCODE_MAX)) begin
            data_frame_r = 1'b0;
            ctrl_frame_r = 1'b1;
        end else begin
            data_frame_r = 1'b0;
            ctrl_frame_r = 1'b0; // 保留Opcode：非数据/控制帧
        end
    end else begin
        data_frame_r = 1'b0;
        ctrl_frame_r = 1'b0;
    end
end

// 步骤3：锁存解析结果并检测错误（时序逻辑）
// 1. 将解析字段和帧类型锁存到输出寄存器
// 2. 检测Opcode错误：状态不匹配/保留Opcode
// 3. 检测QPN错误：解析值与本地/远程QPN均不匹配
always @(posedge clk or negedge rst_n) begin
    if (!rst_n) begin
        // 复位：清空所有输出寄存器和错误标志
        pdu_opcode       <= {OPCODE_WIDTH{1'b0}};
        pdu_qpn          <= {QPN_WIDTH{1'b0}};
        pdu_psn          <= {PSN_WIDTH{1'b0}};
        is_data_frame    <= 1'b0;
        is_control_frame <= 1'b0;
        opcode_err       <= 1'b0;
        qpn_mismatch_err <= 1'b0;
        pdu_parse_done   <= 1'b0;
    end else begin
        if (pdu_valid) begin
            // 锁存解析结果到输出寄存器
            pdu_opcode       <= opcode_r;
            pdu_qpn          <= qpn_r;
            pdu_psn          <= psn_r;
            is_data_frame    <= data_frame_r;
            is_control_frame <= ctrl_frame_r;

            // Opcode错误检测：QP状态不匹配 + 保留Opcode
            case (qp_state)
                RTS: begin
                    // RTS状态：仅接收数据帧 + 排除保留Opcode
                    opcode_err <= (~data_frame_r) || (opcode_r >= RESERVED_OPCODE_MIN);
                end
                RTR: begin
                    // RTR状态：仅接收控制帧 + 排除保留Opcode
                    opcode_err <= (~ctrl_frame_r) || (opcode_r >= RESERVED_OPCODE_MIN);
                end
                INIT, RESET: begin
                    // 初始化/复位状态：所有帧都错误 + 保留Opcode也错误
                    opcode_err <= 1'b1;
                end
                ERROR: begin
                    opcode_err <= 1'b1;
                end
                default: begin
                    opcode_err <= 1'b1;
                end
            endcase

// 移除原独立的保留Opcode判断语句（已整合到case中）
// if (opcode_r >= RESERVED_OPCODE_MIN) begin
//     opcode_err <= 1'b1;
// end  

            // 附加检测：保留Opcode（0x80~0xFF）直接判定为错误
            if (opcode_r >= RESERVED_OPCODE_MIN) begin
                opcode_err <= 1'b1;
            end

            // QPN不匹配错误检测：解析值与本地/远程QPN均不相等
            qpn_mismatch_err <= (qpn_r != local_qpn) && (qpn_r != remote_qpn);

            // 置位解析完成标志
            pdu_parse_done <= 1'b1;
        end else begin
            // PDU无效时：清空错误标志和解析完成标志，保留解析结果
            opcode_err       <= 1'b0;
            qpn_mismatch_err <= 1'b0;
            pdu_parse_done   <= 1'b0;
        end
    end
end

endmodule

verification/tb_rdma_rc_pdu.sv
// RDMA RC PDU解析模块独立测试台
// 功能：脱离QP状态机，通过硬编码模拟QP状态，验证PDU解析、帧类型区分、错误检测逻辑
// 测试用例：覆盖不同QP状态+不同Opcode+有效/无效QPN的核心场景
module tb_rdma_rc_pdu;

// 参数定义（与PDU解析模块对齐）
parameter QPN_WIDTH     = 16;
parameter PSN_WIDTH     = 24;
parameter OPCODE_WIDTH  = 8;
parameter DATA_WIDTH    = 64;
parameter CLK_PERIOD    = 10; // 时钟周期10ns（100MHz）

// PDU字段偏移定义（与PDU解析模块对齐）
parameter OPCODE_OFFSET = 56;
parameter QPN_OFFSET    = 32;
parameter PSN_OFFSET    = 8;

// 信号声明
logic                 clk;
logic                 rst_n;
logic [DATA_WIDTH-1:0] pdu_data;
logic                 pdu_valid;
logic [2:0]           qp_state;   // 模拟QP状态（硬编码）
logic [QPN_WIDTH-1:0] local_qpn;
logic [QPN_WIDTH-1:0] remote_qpn;

// PDU解析模块输出信号
logic [OPCODE_WIDTH-1:0]  pdu_opcode;
logic [QPN_WIDTH-1:0]     pdu_qpn;
logic [PSN_WIDTH-1:0]     pdu_psn;
logic                     is_data_frame;
logic                     is_control_frame;
logic                     opcode_err;
logic                     qpn_mismatch_err;
logic                     pdu_parse_done;

// QP状态定义（与PDU解析模块对齐）
localparam RESET  = 3'b000;
localparam INIT   = 3'b001;
localparam RTR    = 3'b010;
localparam RTS    = 3'b011;
localparam ERROR  = 3'b111;

// Opcode测试值（与PDU解析模块的范围对齐）
localparam DATA_OPCODE     = 8'h05;  // 有效数据帧Opcode（0x00~0x1F）
localparam CTRL_OPCODE     = 8'h25;  // 有效控制帧Opcode（0x20~0x7F）
localparam RESERVED_OPCODE = 8'h85;  // 保留无效Opcode（0x80~0xFF）

// QPN测试值
localparam LOCAL_QPN  = 16'h1234;   // 本地QPN
localparam REMOTE_QPN = 16'h5678;   // 远程QPN
localparam INVALID_QPN = 16'h9999;  // 无效QPN（非本地/远程）

// PSN测试值
localparam TEST_PSN   = 24'h000001;

// 例化PDU解析模块（DUT）
rdma_rc_pdu_parser #(
    .QPN_WIDTH    (QPN_WIDTH),
    .PSN_WIDTH    (PSN_WIDTH),
    .OPCODE_WIDTH (OPCODE_WIDTH),
    .DATA_WIDTH   (DATA_WIDTH)
) u_rdma_rc_pdu_parser (
    .clk            (clk),
    .rst_n          (rst_n),
    .pdu_data       (pdu_data),
    .pdu_valid      (pdu_valid),
    .qp_state       (qp_state),       // 模拟的QP状态
    .local_qpn      (local_qpn),      // 硬编码本地QPN
    .remote_qpn     (remote_qpn),     // 硬编码远程QPN
    .pdu_opcode     (pdu_opcode),
    .pdu_qpn        (pdu_qpn),
    .pdu_psn        (pdu_psn),
    .is_data_frame  (is_data_frame),
    .is_control_frame (is_control_frame),
    .opcode_err     (opcode_err),
    .qpn_mismatch_err (qpn_mismatch_err),
    .pdu_parse_done (pdu_parse_done)
);

// 生成时钟
initial begin
    clk = 1'b0;
    forever #(CLK_PERIOD/2) clk = ~clk;
end

// 修正后的send_pdu任务：添加@(posedge clk)等待时序逻辑更新
task automatic send_pdu(
    input [OPCODE_WIDTH-1:0] opcode,
    input [QPN_WIDTH-1:0]    qpn,
    input [PSN_WIDTH-1:0]    psn
);
    // 定义采样变量，存储有效窗口的结果
    reg opcode_err_sample;
    reg qpn_mismatch_err_sample;
    begin
        pdu_data[OPCODE_OFFSET +: OPCODE_WIDTH] = opcode;
        pdu_data[QPN_OFFSET +: QPN_WIDTH]       = qpn;
        pdu_data[PSN_OFFSET +: PSN_WIDTH]       = psn;
        @(posedge clk);
        pdu_valid = 1'b1;
        $display("[%0t ns] 发送PDU：Opcode=0x%02h, QPN=0x%04h, PSN=0x%06h, QP状态=%03b", 
                 $time, opcode, qpn, psn, qp_state);
        // 2. 等待1个时钟周期，pdu_valid仅持续1个周期（匹配时序图的10~20ns）
        @(posedge clk);
        @(posedge clk);
        pdu_valid = 1'b0;
        #1;              // 避免竞争，延迟1ns
        
        // 3. 采样输出：此时opcode_err正处于20~30ns的有效窗口（核心！）
        opcode_err_sample = opcode_err;
        qpn_mismatch_err_sample = qpn_mismatch_err;
        $display("[%0t ns] 采样结果：Opcode错误标志=%b, QPN不匹配错误标志=%b", 
                 $time, opcode_err_sample, qpn_mismatch_err_sample);

        // 4. 等待错误标志窗口结束，准备下一次PDU
        @(posedge clk);
    end
endtask

// 核心测试激励序列
initial begin
    // 初始化所有信号
    rst_n          = 1'b0;
    pdu_data       = {DATA_WIDTH{1'b0}};
    pdu_valid      = 1'b0;
    qp_state       = RESET;          // 初始QP状态：复位
    local_qpn      = LOCAL_QPN;
    remote_qpn     = REMOTE_QPN;

    // 释放复位
    #20 rst_n = 1'b1;
    $display("[%0t ns] 复位释放", $time);
    #CLK_PERIOD;

    // 测试用例1：QP=RESET状态，发送数据帧（预期Opcode错误）
    qp_state = RESET;
    send_pdu(DATA_OPCODE, LOCAL_QPN, TEST_PSN);
    //$display("[%0t ns] 用例1：RESET状态+数据帧 → Opcode错误标志=%b", $time, opcode_err);

    // 测试用例2：QP=INIT状态，发送控制帧（预期Opcode错误）
    qp_state = INIT;
    send_pdu(CTRL_OPCODE, REMOTE_QPN, TEST_PSN + 1);
    //$display("[%0t ns] 用例2：INIT状态+控制帧 → Opcode错误标志=%b", $time, opcode_err);

    // 测试用例3：QP=RTR状态，发送控制帧（预期无Opcode错误）
    qp_state = RTR;
    send_pdu(CTRL_OPCODE, REMOTE_QPN, TEST_PSN + 2);
    //$display("[%0t ns] 用例3：RTR状态+控制帧 → Opcode错误标志=%b", $time, opcode_err);

    // 测试用例4：QP=RTR状态，发送数据帧（预期Opcode错误）
    qp_state = RTR;
    send_pdu(DATA_OPCODE, LOCAL_QPN, TEST_PSN + 3);
    //$display("[%0t ns] 用例4：RTR状态+数据帧 → Opcode错误标志=%b", $time, opcode_err);

    // 测试用例5：QP=RTS状态，发送数据帧（预期无Opcode错误）
    qp_state = RTS;
    send_pdu(DATA_OPCODE, LOCAL_QPN, TEST_PSN + 4);
    //$display("[%0t ns] 用例5：RTS状态+数据帧 → Opcode错误标志=%b", $time, opcode_err);

    // 测试用例6：QP=RTS状态，发送控制帧（预期Opcode错误）
    qp_state = RTS;
    send_pdu(CTRL_OPCODE, REMOTE_QPN, TEST_PSN + 5);
    //$display("[%0t ns] 用例6：RTS状态+控制帧 → Opcode错误标志=%b", $time, opcode_err);

    // 测试用例7：发送保留Opcode（任意状态均预期Opcode错误）
    qp_state = RTS;
    send_pdu(RESERVED_OPCODE, LOCAL_QPN, TEST_PSN + 6);
    //$display("[%0t ns] 用例7：RTS状态+保留Opcode → Opcode错误标志=%b", $time, opcode_err);

    // 测试用例8：有效数据帧+无效QPN（预期QPN不匹配错误）
    qp_state = RTS;
    send_pdu(DATA_OPCODE, INVALID_QPN, TEST_PSN + 7);
    //$display("[%0t ns] 用例8：RTS状态+有效数据帧+无效QPN → QPN错误标志=%b", $time, qpn_mismatch_err);

    // 结束仿真
    #50 $display("[%0t ns] PDU解析模块独立测试完成", $time);
    $finish;
end

// 波形Dump（用于仿真调试）
initial begin
    $dumpfile("../sim/wave/tb_rdma_rc_pdu.vcd");
    $dumpvars(0, tb_rdma_rc_pdu);
    $dumpflush;

    // FSDB Dump（Verdi调试用，可选）
    $fsdbDumpfile("../sim/wave/tb_rdma_rc_pdu.fsdb");
    $fsdbDumpvars(0, tb_rdma_rc_pdu);
    $fsdbDumpMDA();
end

endmodule

sim/wave/tb_rdma_rc_pdu.vcd
$date
	Wed Nov 26 00:08:57 2025
$end

$version
	Synopsys VCS version O-2018.09-SP2_Full64
$end

$timescale
	1ps
$end

$comment Csum: 1 688b92e36ea0bd18 $end


$scope module tb_rdma_rc_pdu $end
$var reg 1 ! clk $end
$var reg 1 " rst_n $end
$var reg 64 # pdu_data [63:0] $end
$var reg 1 $ pdu_valid $end
$var reg 3 % qp_state [2:0] $end
$var reg 16 & local_qpn [15:0] $end
$var reg 16 ' remote_qpn [15:0] $end
$var reg 8 ( pdu_opcode [7:0] $end
$var reg 16 ) pdu_qpn [15:0] $end
$var reg 24 * pdu_psn [23:0] $end
$var reg 1 + is_data_frame $end
$var reg 1 , is_control_frame $end
$var reg 1 - opcode_err $end
$var reg 1 . qpn_mismatch_err $end
$var reg 1 / pdu_parse_done $end

$scope module u_rdma_rc_pdu_parser $end
$var wire 1 0 clk $end
$var wire 1 1 rst_n $end
$var wire 64 2 pdu_data [63:0] $end
$var wire 1 3 pdu_valid $end
$var wire 3 4 qp_state [2:0] $end
$var wire 16 5 local_qpn [15:0] $end
$var wire 16 6 remote_qpn [15:0] $end
$var reg 8 7 pdu_opcode [7:0] $end
$var reg 16 8 pdu_qpn [15:0] $end
$var reg 24 9 pdu_psn [23:0] $end
$var reg 1 : is_data_frame $end
$var reg 1 ; is_control_frame $end
$var reg 1 < opcode_err $end
$var reg 1 = qpn_mismatch_err $end
$var reg 1 > pdu_parse_done $end
$var reg 8 ? opcode_r [7:0] $end
$var reg 16 @ qpn_r [15:0] $end
$var reg 24 A psn_r [23:0] $end
$var reg 1 B data_frame_r $end
$var reg 1 C ctrl_frame_r $end
$upscope $end

$upscope $end

$enddefinitions $end

#0
$dumpvars
0!
0C
0B
0,
0+
0-
0/
0$
0.
0"
0;
0:
0<
0>
03
0=
01
b0001001000110100 &
b00000000 ?
b0000000000000000000000000000000000000000000000000000000000000000 #
b00000000 (
b000000000000000000000000 *
b0000000000000000 )
b000000000000000000000000 A
b000 %
b0000000000000000 @
b0101011001111000 '
b0001001000110100 5
b0000000000000000000000000000000000000000000000000000000000000000 2
b00000000 7
b000000000000000000000000 9
b0000000000000000 8
b000 4
b0101011001111000 6
00
$end
#5000
1!
10
#10000
0!
00
#15000
1!
10
#20000
1"
11
0!
00
#25000
1!
10
#30000
b0000010100000000000100100011010000000000000000000000000100000000 #
b0000010100000000000100100011010000000000000000000000000100000000 2
1$
13
0!
00
b000000000000000000000001 A
b0001001000110100 @
b00000101 ?
1B
#35000
1!
10
b00000101 7
b00000101 (
b0001001000110100 8
b0001001000110100 )
b000000000000000000000001 9
b000000000000000000000001 *
1:
1+
1<
1-
1>
1/
#40000
0$
03
0!
00
b000000000000000000000000 A
b0000000000000000 @
b00000000 ?
0B
#45000
1!
10
0<
0-
0>
0/
#46000
b001 %
b001 4
b0010010100000000010101100111100000000000000000000000001000000000 #
b0010010100000000010101100111100000000000000000000000001000000000 2
1$
13
b000000000000000000000010 A
b0101011001111000 @
b00100101 ?
1C
#50000
0!
00
#55000
1!
10
b00100101 7
b00100101 (
b0101011001111000 8
b0101011001111000 )
b000000000000000000000010 9
b000000000000000000000010 *
0:
0+
1;
1,
1<
1-
1>
1/
#56000
0$
03
b000000000000000000000000 A
b0000000000000000 @
b00000000 ?
0C
#60000
0!
00
#65000
1!
10
0<
0-
0>
0/
#66000
b010 %
b010 4
b0010010100000000010101100111100000000000000000000000001100000000 #
b0010010100000000010101100111100000000000000000000000001100000000 2
1$
13
b000000000000000000000011 A
b0101011001111000 @
b00100101 ?
1C
#70000
0!
00
#75000
1!
10
b000000000000000000000011 9
b000000000000000000000011 *
1>
1/
#76000
0$
03
b000000000000000000000000 A
b0000000000000000 @
b00000000 ?
0C
#80000
0!
00
#85000
1!
10
0>
0/
#86000
b0000010100000000000100100011010000000000000000000000010000000000 #
b0000010100000000000100100011010000000000000000000000010000000000 2
1$
13
b000000000000000000000100 A
b0001001000110100 @
b00000101 ?
1B
#90000
0!
00
#95000
1!
10
b00000101 7
b00000101 (
b0001001000110100 8
b0001001000110100 )
b000000000000000000000100 9
b000000000000000000000100 *
1:
1+
0;
0,
1<
1-
1>
1/
#96000
0$
03
b000000000000000000000000 A
b0000000000000000 @
b00000000 ?
0B
#100000
0!
00
#105000
1!
10
0<
0-
0>
0/
#106000
b011 %
b011 4
b0000010100000000000100100011010000000000000000000000010100000000 #
b0000010100000000000100100011010000000000000000000000010100000000 2
1$
13
b000000000000000000000101 A
b0001001000110100 @
b00000101 ?
1B
#110000
0!
00
#115000
1!
10
b000000000000000000000101 9
b000000000000000000000101 *
1>
1/
#116000
0$
03
b000000000000000000000000 A
b0000000000000000 @
b00000000 ?
0B
#120000
0!
00
#125000
1!
10
0>
0/
#126000
b0010010100000000010101100111100000000000000000000000011000000000 #
b0010010100000000010101100111100000000000000000000000011000000000 2
1$
13
b000000000000000000000110 A
b0101011001111000 @
b00100101 ?
1C
#130000
0!
00
#135000
1!
10
b00100101 7
b00100101 (
b0101011001111000 8
b0101011001111000 )
b000000000000000000000110 9
b000000000000000000000110 *
0:
0+
1;
1,
1<
1-
1>
1/
#136000
0$
03
b000000000000000000000000 A
b0000000000000000 @
b00000000 ?
0C
#140000
0!
00
#145000
1!
10
0<
0-
0>
0/
#146000
b1000010100000000000100100011010000000000000000000000011100000000 #
b1000010100000000000100100011010000000000000000000000011100000000 2
1$
13
b000000000000000000000111 A
b0001001000110100 @
b10000101 ?
#150000
0!
00
#155000
1!
10
b10000101 7
b10000101 (
b0001001000110100 8
b0001001000110100 )
b000000000000000000000111 9
b000000000000000000000111 *
0;
0,
1<
1-
1>
1/
#156000
0$
03
b000000000000000000000000 A
b0000000000000000 @
b00000000 ?
#160000
0!
00
#165000
1!
10
0<
0-
0>
0/
#166000
b0000010100000000100110011001100100000000000000000000100000000000 #
b0000010100000000100110011001100100000000000000000000100000000000 2
1$
13
b000000000000000000001000 A
b1001100110011001 @
b00000101 ?
1B
#170000
0!
00
#175000
1!
10
b00000101 7
b00000101 (
b1001100110011001 8
b1001100110011001 )
b000000000000000000001000 9
b000000000000000000001000 *
1:
1+
1=
1.
1>
1/
#176000
0$
03
b000000000000000000000000 A
b0000000000000000 @
b00000000 ?
0B
#180000
0!
00
#185000
1!
10
0=
0.
0>
0/
